{
  "updatedAt": "2026-06-17T14:24:06+08:00",
  "source": {
    "market": "Sina Finance hq.sinajs.cn",
    "weather": "Open-Meteo"
  },
  "index": {
    "name": "上证指数",
    "code": "000001.SH",
    "price": 4087.09,
    "change": -4.8,
    "changePct": -0.12,
    "open": 4074.29,
    "high": 4098.7,
    "low": 4073.73,
    "volume": 527007553,
    "amount": 1220219952007.0,
    "trend": "窄幅震荡",
    "risk": "观察",
    "quoteTime": "2026-06-17T14:24:02+08:00",
    "volumeTone": "成交额约12202亿",
    "series": [
      4092.0,
      4094.35,
      4095.18,
      4095.49,
      4097.61,
      4094.43,
      4093.59,
      4092.9,
      4095.58,
      4094.07,
      4093.64,
      4092.27,
      4091.82,
      4092.76,
      4092.9,
      4094.09,
      4090.95,
      4089.75,
      4089.11,
      4089.08,
      4089.62,
      4090.8,
      4091.82,
      4092.32,
      4093.97,
      4092.33,
      4090.8,
      4092.7,
      4092.33,
      4090.18,
      4092.09,
      4092.89,
      4093.11,
      4093.49,
      4091.37,
      4086.7,
      4087.71,
      4089.67,
      4088.82,
      4091.9,
      4090.45,
      4092.01,
      4090.16,
      4088.81,
      4090.93,
      4088.86,
      4088.42,
      4087.11
    ]
  },
  "stocks": [
    {
      "name": "兴蓉环境",
      "code": "000598.SZ",
      "price": 6.88,
      "change": -0.04,
      "changePct": -0.58,
      "open": 6.91,
      "high": 6.96,
      "low": 6.83,
      "volume": 18472173,
      "amount": 127253946.65,
      "trend": "盘中偏弱",
      "risk": "跟随指数",
      "quoteTime": "2026-06-17T14:24:03+08:00"
    },
    {
      "name": "华润三九",
      "code": "000999.SZ",
      "price": 23.71,
      "change": -0.54,
      "changePct": -2.23,
      "open": 24.2,
      "high": 24.24,
      "low": 23.69,
      "volume": 7461320,
      "amount": 178059219.19,
      "trend": "盘中偏弱",
      "risk": "弱于指数",
      "quoteTime": "2026-06-17T14:24:03+08:00"
    },
    {
      "name": "光启技术",
      "code": "002625.SZ",
      "price": 37.87,
      "change": -0.13,
      "changePct": -0.34,
      "open": 38.02,
      "high": 38.65,
      "low": 37.85,
      "volume": 20132418,
      "amount": 767397077.69,
      "trend": "盘中偏弱",
      "risk": "跟随指数",
      "quoteTime": "2026-06-17T14:24:00+08:00"
    },
    {
      "name": "迅游科技",
      "code": "300467.SZ",
      "price": 33.59,
      "change": -0.77,
      "changePct": -2.24,
      "open": 34.01,
      "high": 34.98,
      "low": 33.51,
      "volume": 5388658,
      "amount": 183941338.22,
      "trend": "盘中偏弱",
      "risk": "弱于指数",
      "quoteTime": "2026-06-17T14:23:57+08:00"
    },
    {
      "name": "伊利股份",
      "code": "600887.SH",
      "price": 24.65,
      "change": -0.15,
      "changePct": -0.6,
      "open": 24.85,
      "high": 24.89,
      "low": 24.51,
      "volume": 43894924,
      "amount": 1081813464.0,
      "trend": "盘中偏弱",
      "risk": "跟随指数",
      "quoteTime": "2026-06-17T14:24:02+08:00"
    }
  ],
  "weather": {
    "city": "深圳",
    "condition": "雷雨",
    "temperature": 26,
    "humidity": 93,
    "wind": "南风 11km/h"
  },
  "ui": {
    "eyebrow": "A股观察"
  }
}
