{
  "updatedAt": "2026-07-01T11:00:39+08:00",
  "source": {
    "market": "Sina Finance hq.sinajs.cn",
    "weather": "Open-Meteo"
  },
  "index": {
    "name": "上证指数",
    "code": "000001.SH",
    "price": 4136.0,
    "change": 41.6,
    "changePct": 1.02,
    "open": 4090.76,
    "high": 4139.6,
    "low": 4087.54,
    "volume": 391884026,
    "amount": 989855772694.0,
    "trend": "指数偏强",
    "risk": "相对强",
    "quoteTime": "2026-07-01T11:00:35+08:00",
    "volumeTone": "成交额约9899亿",
    "series": [
      4110.98,
      4111.48,
      4107.58,
      4111.39,
      4113.18,
      4112.96,
      4117.03,
      4119.08,
      4120.4,
      4115.87,
      4117.46,
      4117.8,
      4117.45,
      4117.34,
      4116.09,
      4114.15,
      4116.06,
      4121.09,
      4119.77,
      4117.54,
      4120.19,
      4118.28,
      4119.04,
      4119.21,
      4116.01,
      4116.7,
      4122.8,
      4123.0,
      4117.29,
      4114.97,
      4114.82,
      4119.0,
      4125.37,
      4129.5,
      4129.14,
      4125.22,
      4128.56,
      4134.56,
      4138.36,
      4138.17,
      4136.98,
      4134.95,
      4135.35,
      4135.51,
      4137.4,
      4138.12,
      4139.02,
      4137.26
    ]
  },
  "stocks": [
    {
      "name": "兴蓉环境",
      "code": "000598.SZ",
      "price": 6.47,
      "change": 0.05,
      "changePct": 0.78,
      "open": 6.4,
      "high": 6.49,
      "low": 6.4,
      "volume": 10420918,
      "amount": 67088571.25,
      "trend": "盘中偏强",
      "risk": "跟随指数",
      "quoteTime": "2026-07-01T11:00:36+08:00"
    },
    {
      "name": "华润三九",
      "code": "000999.SZ",
      "price": 22.91,
      "change": 0.42,
      "changePct": 1.87,
      "open": 22.51,
      "high": 23.07,
      "low": 22.25,
      "volume": 5855701,
      "amount": 132832282.89,
      "trend": "盘中偏强",
      "risk": "跟随指数",
      "quoteTime": "2026-07-01T11:00:36+08:00"
    },
    {
      "name": "光启技术",
      "code": "002625.SZ",
      "price": 31.35,
      "change": 1.03,
      "changePct": 3.4,
      "open": 31.21,
      "high": 32.15,
      "low": 30.9,
      "volume": 31502357,
      "amount": 992124221.69,
      "trend": "盘中偏强",
      "risk": "强于指数",
      "quoteTime": "2026-07-01T11:00:33+08:00"
    },
    {
      "name": "迅游科技",
      "code": "300467.SZ",
      "price": 34.08,
      "change": -3.1,
      "changePct": -8.34,
      "open": 37.37,
      "high": 37.67,
      "low": 32.98,
      "volume": 9074900,
      "amount": 315728391.0,
      "trend": "盘中偏弱",
      "risk": "弱于指数",
      "quoteTime": "2026-07-01T11:00:33+08:00"
    },
    {
      "name": "伊利股份",
      "code": "600887.SH",
      "price": 24.35,
      "change": 0.39,
      "changePct": 1.63,
      "open": 24.0,
      "high": 24.55,
      "low": 23.76,
      "volume": 34156201,
      "amount": 824228702.0,
      "trend": "盘中偏强",
      "risk": "跟随指数",
      "quoteTime": "2026-07-01T11:00:36+08:00"
    }
  ],
  "weather": {
    "city": "深圳",
    "condition": "阴",
    "temperature": 32,
    "humidity": 61,
    "wind": "东南风 10km/h"
  },
  "ui": {
    "eyebrow": "A股观察"
  }
}
