{
  "updatedAt": "2026-06-22T23:30:39+08:00",
  "source": {
    "market": "Sina Finance 美股 hq.sinajs.cn",
    "weather": "Open-Meteo"
  },
  "index": {
    "name": "纳斯达克指数",
    "code": "IXIC",
    "price": 26229.78,
    "change": -288.15,
    "changePct": -1.09,
    "open": 26483.31,
    "high": 26561.12,
    "low": 26156.46,
    "volume": 6287934086,
    "amount": 9652383415.0,
    "trend": "指数偏弱",
    "risk": "观察",
    "quoteTime": "2026-06-22T23:30:38+08:00",
    "volumeTone": "成交额约97亿",
    "series": []
  },
  "stocks": [
    {
      "name": "SPCX",
      "code": "SPCX",
      "price": 169.28,
      "change": -15.72,
      "changePct": -8.5,
      "open": 176.04,
      "high": 176.75,
      "low": 165.12,
      "volume": 68818084,
      "amount": 157435334.0,
      "trend": "盘中偏弱",
      "risk": "弱于指数",
      "quoteTime": "2026-06-22T23:30:38+08:00"
    },
    {
      "name": "苹果",
      "code": "AAPL",
      "price": 299.8,
      "change": 1.79,
      "changePct": 0.6,
      "open": 297.31,
      "high": 302.42,
      "low": 297.31,
      "volume": 13006214,
      "amount": 56183282.0,
      "trend": "盘中偏强",
      "risk": "强于指数",
      "quoteTime": "2026-06-22T23:30:38+08:00"
    },
    {
      "name": "谷歌",
      "code": "GOOG",
      "price": 343.3,
      "change": -24.16,
      "changePct": -6.57,
      "open": 357.13,
      "high": 358.2,
      "low": 340.94,
      "volume": 13664787,
      "amount": 20743594.0,
      "trend": "盘中偏弱",
      "risk": "弱于指数",
      "quoteTime": "2026-06-22T23:30:38+08:00"
    },
    {
      "name": "特斯拉",
      "code": "TSLA",
      "price": 409.86,
      "change": 9.37,
      "changePct": 2.34,
      "open": 394.85,
      "high": 414.75,
      "low": 394.4,
      "volume": 23760135,
      "amount": 52015606.0,
      "trend": "盘中偏强",
      "risk": "强于指数",
      "quoteTime": "2026-06-22T23:30:38+08:00"
    },
    {
      "name": "微软",
      "code": "MSFT",
      "price": 371.06,
      "change": -8.34,
      "changePct": -2.2,
      "open": 375.74,
      "high": 381.63,
      "low": 370.57,
      "volume": 13512297,
      "amount": 38238286.0,
      "trend": "盘中偏弱",
      "risk": "弱于指数",
      "quoteTime": "2026-06-22T23:30:38+08:00"
    },
    {
      "name": "博通",
      "code": "AVGO",
      "price": 395.03,
      "change": -15.67,
      "changePct": -3.82,
      "open": 413.66,
      "high": 414.64,
      "low": 392.83,
      "volume": 9916832,
      "amount": 37533198.0,
      "trend": "盘中偏弱",
      "risk": "弱于指数",
      "quoteTime": "2026-06-22T23:30:38+08:00"
    },
    {
      "name": "可口可乐",
      "code": "KO",
      "price": 79.53,
      "change": 0.14,
      "changePct": 0.18,
      "open": 79.25,
      "high": 79.81,
      "low": 79.06,
      "volume": 4259681,
      "amount": 20756358.0,
      "trend": "盘中偏强",
      "risk": "强于指数",
      "quoteTime": "2026-06-22T23:30:38+08:00"
    }
  ],
  "weather": {
    "city": "深圳",
    "condition": "晴",
    "temperature": 27,
    "humidity": 88,
    "wind": "南风 10km/h"
  },
  "ui": {
    "eyebrow": "美股观察"
  }
}
