{
  "updatedAt": "2026-06-19T00:00:54+08:00",
  "source": {
    "market": "Sina Finance 美股 hq.sinajs.cn",
    "weather": "Open-Meteo"
  },
  "index": {
    "name": "纳斯达克指数",
    "code": "IXIC",
    "price": 26384.14,
    "change": 362.49,
    "changePct": 1.39,
    "open": 26410.62,
    "high": 26431.96,
    "low": 26188.69,
    "volume": 8627797713,
    "amount": 9116473784.0,
    "trend": "指数偏强",
    "risk": "相对强",
    "quoteTime": "2026-06-19T00:00:53+08:00",
    "volumeTone": "成交额约91亿",
    "series": [
      26394.75,
      26393.17,
      26370.17,
      26373.94,
      26373.91,
      26363.32,
      26358.97,
      26351.64,
      26361.49,
      26358.53,
      26344.46,
      26343.42,
      26334.09,
      26341.65,
      26343.9,
      26358.42,
      26335.67,
      26322.34,
      26335.0,
      26327.85,
      26320.76,
      26311.54,
      26320.71,
      26316.15,
      26301.48,
      26299.09,
      26269.32,
      26293.46,
      26289.98,
      26306.21,
      26304.48,
      26294.89,
      26289.53,
      26280.93,
      26276.29,
      26288.63,
      26286.52,
      26303.42,
      26323.39,
      26331.57,
      26353.13,
      26365.14,
      26358.82,
      26378.61,
      26370.87,
      26379.85,
      26385.61,
      26373.91
    ]
  },
  "stocks": [
    {
      "name": "SPCX",
      "code": "SPCX",
      "price": 176.32,
      "change": -15.5,
      "changePct": -8.08,
      "open": 188.39,
      "high": 188.41,
      "low": 175.26,
      "volume": 99673237,
      "amount": 130222675.0,
      "trend": "盘中偏弱",
      "risk": "弱于指数",
      "quoteTime": "2026-06-19T00:00:53+08:00"
    },
    {
      "name": "苹果",
      "code": "AAPL",
      "price": 297.68,
      "change": 1.73,
      "changePct": 0.58,
      "open": 298.11,
      "high": 300.57,
      "low": 295.62,
      "volume": 36550754,
      "amount": 52073977.0,
      "trend": "红盘震荡",
      "risk": "跟随指数",
      "quoteTime": "2026-06-19T00:00:53+08:00"
    },
    {
      "name": "谷歌",
      "code": "GOOG",
      "price": 364.01,
      "change": 1.91,
      "changePct": 0.53,
      "open": 363.89,
      "high": 365.95,
      "low": 356.61,
      "volume": 9178169,
      "amount": 21584293.0,
      "trend": "盘中偏强",
      "risk": "跟随指数",
      "quoteTime": "2026-06-19T00:00:53+08:00"
    },
    {
      "name": "特斯拉",
      "code": "TSLA",
      "price": 391.17,
      "change": -5.21,
      "changePct": -1.31,
      "open": 398.1,
      "high": 399.0,
      "low": 384.7,
      "volume": 25066132,
      "amount": 49709461.0,
      "trend": "盘中偏弱",
      "risk": "弱于指数",
      "quoteTime": "2026-06-19T00:00:53+08:00"
    },
    {
      "name": "微软",
      "code": "MSFT",
      "price": 378.04,
      "change": -0.88,
      "changePct": -0.23,
      "open": 377.82,
      "high": 379.62,
      "low": 373.28,
      "volume": 24749853,
      "amount": 34956848.0,
      "trend": "绿盘震荡",
      "risk": "弱于指数",
      "quoteTime": "2026-06-19T00:00:53+08:00"
    },
    {
      "name": "博通",
      "code": "AVGO",
      "price": 408.68,
      "change": 15.78,
      "changePct": 4.02,
      "open": 409.58,
      "high": 412.5,
      "low": 405.38,
      "volume": 14321307,
      "amount": 41123552.0,
      "trend": "红盘震荡",
      "risk": "强于指数",
      "quoteTime": "2026-06-19T00:00:53+08:00"
    },
    {
      "name": "可口可乐",
      "code": "KO",
      "price": 78.92,
      "change": -1.02,
      "changePct": -1.27,
      "open": 79.87,
      "high": 80.01,
      "low": 78.76,
      "volume": 9018042,
      "amount": 18006725.0,
      "trend": "盘中偏弱",
      "risk": "弱于指数",
      "quoteTime": "2026-06-19T00:00:53+08:00"
    }
  ],
  "weather": {
    "city": "深圳",
    "condition": "阴",
    "temperature": 26,
    "humidity": 96,
    "wind": "南风 12km/h"
  },
  "ui": {
    "eyebrow": "美股观察"
  }
}
