{
  "updatedAt": "2026-07-01T06:00:40+08:00",
  "source": {
    "market": "Sina Finance 美股 hq.sinajs.cn",
    "weather": "Open-Meteo"
  },
  "index": {
    "name": "纳斯达克指数",
    "code": "IXIC",
    "price": 26213.72,
    "change": 393.58,
    "changePct": 1.52,
    "open": 25824.47,
    "high": 26253.04,
    "low": 25808.06,
    "volume": 8864736162,
    "amount": 10642493366.0,
    "trend": "指数偏强",
    "risk": "相对强",
    "quoteTime": "2026-07-01T06:00:38+08:00",
    "volumeTone": "成交额约106亿",
    "series": []
  },
  "stocks": [
    {
      "name": "SPCX",
      "code": "SPCX",
      "price": 170.86,
      "change": 6.67,
      "changePct": 4.06,
      "open": 163.38,
      "high": 172.4,
      "low": 161.64,
      "volume": 80865720,
      "amount": 172394238.0,
      "trend": "盘中偏强",
      "risk": "强于指数",
      "quoteTime": "2026-07-01T06:00:38+08:00"
    },
    {
      "name": "苹果",
      "code": "AAPL",
      "price": 289.36,
      "change": 7.62,
      "changePct": 2.7,
      "open": 281.17,
      "high": 289.94,
      "low": 280.69,
      "volume": 65040819,
      "amount": 79974263.0,
      "trend": "盘中偏强",
      "risk": "强于指数",
      "quoteTime": "2026-07-01T06:00:38+08:00"
    },
    {
      "name": "谷歌",
      "code": "GOOG",
      "price": 353.33,
      "change": 2.05,
      "changePct": 0.58,
      "open": 350.96,
      "high": 355.39,
      "low": 348.11,
      "volume": 21151234,
      "amount": 29277223.0,
      "trend": "盘中偏强",
      "risk": "跟随指数",
      "quoteTime": "2026-07-01T06:00:38+08:00"
    },
    {
      "name": "特斯拉",
      "code": "TSLA",
      "price": 420.6,
      "change": 8.76,
      "changePct": 2.13,
      "open": 406.0,
      "high": 424.54,
      "low": 406.0,
      "volume": 43046034,
      "amount": 46445582.0,
      "trend": "盘中偏强",
      "risk": "跟随指数",
      "quoteTime": "2026-07-01T06:00:38+08:00"
    },
    {
      "name": "微软",
      "code": "MSFT",
      "price": 373.02,
      "change": 4.45,
      "changePct": 1.21,
      "open": 371.03,
      "high": 374.15,
      "low": 367.45,
      "volume": 44820152,
      "amount": 59959504.0,
      "trend": "盘中偏强",
      "risk": "跟随指数",
      "quoteTime": "2026-07-01T06:00:38+08:00"
    },
    {
      "name": "博通",
      "code": "AVGO",
      "price": 377.75,
      "change": 5.3,
      "changePct": 1.42,
      "open": 374.79,
      "high": 379.62,
      "low": 370.64,
      "volume": 28483748,
      "amount": 32105006.0,
      "trend": "盘中偏强",
      "risk": "跟随指数",
      "quoteTime": "2026-07-01T06:00:38+08:00"
    },
    {
      "name": "可口可乐",
      "code": "KO",
      "price": 81.27,
      "change": -1.38,
      "changePct": -1.67,
      "open": 82.5,
      "high": 82.54,
      "low": 81.01,
      "volume": 16403803,
      "amount": 24463000.0,
      "trend": "盘中偏弱",
      "risk": "弱于指数",
      "quoteTime": "2026-07-01T06:00:38+08:00"
    }
  ],
  "weather": {
    "city": "深圳",
    "condition": "阴",
    "temperature": 26,
    "humidity": 92,
    "wind": "东风 5km/h"
  },
  "ui": {
    "eyebrow": "美股观察"
  }
}
